{
  "bbox": {
    "parking": {
      "total_area": 647414.7349613062,
      "year1_cost": 26839574.60044619
    },
    "roads": {
      "total_area": 3692084.583455802,
      "year1_cost": 154011064.93807006
    },
    "sidewalks": {
      "total_area": 87410.04010621733,
      "year1_cost": 2125893.259378077
    }
  },
  "city": {
    "parking": {
      "total_area": 647414.7349613062,
      "year1_cost": 26839574.60044619
    },
    "roads": {
      "total_area": 3052209.5244511357,
      "year1_cost": 128125585.30705144
    },
    "sidewalks": {
      "total_area": 87410.04010621733,
      "year1_cost": 2125893.259378077
    }
  }
}