{
  "bbox": {
    "parking": {
      "total_area": 2194598.4900351195,
      "year1_cost": 52645647.36831057
    },
    "roads": {
      "total_area": 14236256.366608644,
      "year1_cost": 341733592.29158616
    },
    "sidewalks": {
      "total_area": 1842264.8765002314,
      "year1_cost": 25303349.354306705
    }
  },
  "city": {
    "parking": {
      "total_area": 2193545.0740072033,
      "year1_cost": 52620377.24760758
    },
    "roads": {
      "total_area": 11087335.644676356,
      "year1_cost": 269944546.2621293
    },
    "sidewalks": {
      "total_area": 1842264.8765002314,
      "year1_cost": 25303349.354306705
    }
  }
}