{
  "project_name": "Campbell, CA",
  "bbox": [
    37.2543718,
    -121.9920268,
    37.3069915,
    -121.9180402
  ],
  "center_lon": -121.9550335,
  "center_lat": 37.280681650000005,
  "snapshot_date": "2026-06-19",
  "stats": [
    {
      "type": "roads",
      "color": "#6b7280",
      "total_area": 1999906.9192766182,
      "feature_count": 7274
    },
    {
      "type": "parking",
      "color": "#3b82f6",
      "total_area": 483980.48244189005,
      "feature_count": 350
    },
    {
      "type": "sidewalks",
      "color": "#f59e0b",
      "total_area": 312715.9972443278,
      "feature_count": 2408
    }
  ],
  "city_area": 15392891.878709825,
  "total_paved": 2683371.899824652,
  "pct_paved": 17.432539128895396
}