[
  {
    "slug": "beaverton-or",
    "name": "Beaverton, OR",
    "bbox": [
      45.4245861,
      -122.8777172,
      45.5429639,
      -122.7436553
    ],
    "center_lon": -122.81068625,
    "center_lat": 45.483774999999994
  },
  {
    "slug": "gresham-or",
    "name": "Gresham, OR",
    "bbox": [
      45.46094,
      -122.4980699,
      45.5608795,
      -122.3675829
    ],
    "center_lon": -122.43282640000001,
    "center_lat": 45.510909749999996
  },
  {
    "slug": "hillsboro-or",
    "name": "Hillsboro, OR",
    "bbox": [
      45.4763623,
      -123.0118142,
      45.5765184,
      -122.8595375
    ],
    "center_lon": -122.93567585,
    "center_lat": 45.52644035
  },
  {
    "slug": "lake-oswego-or",
    "name": "Lake Oswego, OR",
    "bbox": [
      45.3822911,
      -122.7477826,
      45.4403461,
      -122.6425235
    ],
    "center_lon": -122.69515304999999,
    "center_lat": 45.4113186
  },
  {
    "slug": "milwaukie-or",
    "name": "Milwaukie, OR",
    "bbox": [
      45.4246949,
      -122.6522507,
      45.4622158,
      -122.5817455
    ],
    "center_lon": -122.61699809999999,
    "center_lat": 45.44345535
  },
  {
    "slug": "portland-or",
    "name": "Portland, OR",
    "bbox": [
      45.432536,
      -122.8367489,
      45.6508706,
      -122.4720252
    ],
    "center_lon": -122.65438705,
    "center_lat": 45.541703299999995
  },
  {
    "slug": "tigard-or",
    "name": "Tigard, OR",
    "bbox": [
      45.3933306,
      -122.8569241,
      45.4564334,
      -122.7434206
    ],
    "center_lon": -122.80017235,
    "center_lat": 45.424882
  }
]